avachain/__init__.py
avachain/avachain.py
avachain/avachain_executor.py
avachain/avachain_utils.py
avachain/persona_creator.py
avachain/tool_creator.py
avachain-2.1.4.dist-info/licenses/LICENSE
avachain-2.1.4.dist-info/METADATA
avachain-2.1.4.dist-info/WHEEL
avachain-2.1.4.dist-info/top_level.txt
avachain-2.1.4.dist-info/RECORD
