Metadata-Version: 2.4
Name: avachain
Version: 2.1.4
Summary: A lightweight library for creating and running AI agents with tools, supporting OpenAI-compatible APIs
Home-page: https://github.com/OnlinePage/Avachain
Author: Salo Soja Edwin
Author-email: salosoja@gmail.com
License: MIT
Project-URL: Bug Reports, https://github.com/OnlinePage/Avachain/issues
Project-URL: Source, https://github.com/OnlinePage/Avachain
Project-URL: Documentation, https://github.com/OnlinePage/Avachain#readme
Keywords: ai,agent,llm,openai,tools,chatbot,automation,artificial-intelligence,machine-learning,nlp,conversational-ai,function-calling,streaming,claude,mistral,gpt
Classifier: Development Status :: 4 - Beta
Classifier: Intended Audience :: Developers
Classifier: Intended Audience :: Science/Research
Classifier: Intended Audience :: Information Technology
Classifier: Topic :: Scientific/Engineering :: Artificial Intelligence
Classifier: Topic :: Software Development :: Libraries :: Python Modules
Classifier: Topic :: Internet :: WWW/HTTP :: Dynamic Content :: CGI Tools/Libraries
Classifier: License :: OSI Approved :: MIT License
Classifier: Programming Language :: Python :: 3.10
Classifier: Programming Language :: Python :: 3.11
Classifier: Operating System :: OS Independent
Classifier: Environment :: Console
Classifier: Environment :: Web Environment
Requires-Python: >=3.10
License-File: LICENSE
Requires-Dist: pydantic<3.0.0,>=2.6.1
Requires-Dist: requests<3.0.0,>=2.31.0
Requires-Dist: tokenizers<1.0.0,>=0.19.1
Requires-Dist: openai<2.0.0,>=1.63.0
Requires-Dist: numpy>=1.21.0
Requires-Dist: print-color>=0.4.0
Provides-Extra: dev
Requires-Dist: pytest>=6.0.0; extra == "dev"
Requires-Dist: pytest-cov>=2.0.0; extra == "dev"
Requires-Dist: black>=22.0.0; extra == "dev"
Requires-Dist: isort[colors]>=5.0.0; extra == "dev"
Requires-Dist: flake8>=6.0.0; extra == "dev"
Requires-Dist: mypy>=0.910; extra == "dev"
Requires-Dist: pre-commit>=2.15.0; extra == "dev"
Requires-Dist: colorama>=0.4.0; extra == "dev"
Provides-Extra: docs
Requires-Dist: sphinx>=4.0.0; extra == "docs"
Requires-Dist: sphinx-rtd-theme>=1.0.0; extra == "docs"
Requires-Dist: myst-parser>=0.17.0; extra == "docs"
Provides-Extra: examples
Requires-Dist: jupyter>=1.0.0; extra == "examples"
Requires-Dist: matplotlib>=3.5.0; extra == "examples"
Requires-Dist: pandas>=1.3.0; extra == "examples"
Dynamic: author
Dynamic: author-email
Dynamic: classifier
Dynamic: description
Dynamic: description-content-type
Dynamic: home-page
Dynamic: keywords
Dynamic: license
Dynamic: license-file
Dynamic: project-url
Dynamic: provides-extra
Dynamic: requires-dist
Dynamic: requires-python
Dynamic: summary
